marulib/__init__.py
marulib/async_logger.py
marulib/math_helpers.py
marulib/string_helpers.py
pymarulib-0.1.1.dist-info/licenses/LICENSE
pymarulib-0.1.1.dist-info/METADATA
pymarulib-0.1.1.dist-info/WHEEL
pymarulib-0.1.1.dist-info/top_level.txt
pymarulib-0.1.1.dist-info/RECORD
