Metadata-Version: 2.4
Name: pymarulib
Version: 0.1.1
Summary: A personal collection of utility functions.
Author-email: Maru <maru@fuwamofu.net>
License: Copyright (c) [2025] [Sunoh Ryu]
Project-URL: Homepage, https://www.google.com/search?q=https://github.com/EukkMaru/pymarulib
Project-URL: Bug Tracker, https://www.google.com/search?q=https://github.com/EukkMaru/pymarulib/issues
Classifier: Programming Language :: Python :: 3
Classifier: License :: OSI Approved :: MIT License
Classifier: Operating System :: OS Independent
Requires-Python: >=3.8
License-File: LICENSE
Dynamic: license-file
